pyopenet/ETException.py
pyopenet/ETJob.py
pyopenet/ETRequest.py
pyopenet/ETTypes.py
pyopenet/ETUtils.py
pyopenet/__init__.py
pyopenet/py.typed
pyopenet-0.1.1b0.dist-info/METADATA
pyopenet-0.1.1b0.dist-info/WHEEL
pyopenet-0.1.1b0.dist-info/licenses/LICENSE
pyopenet-0.1.1b0.dist-info/RECORD
