Metadata-Version: 2.4
Name: pyopenet
Version: 0.1.1b0
Summary: Retrieve mass amounts of data from OpenET with ease
Author-email: Robin Fishman <13447870+aetriusgx@users.noreply.github.com>
License-File: LICENSE
Requires-Python: >=3.12
Requires-Dist: gcp-storage-emulator>=2024.8.3
Requires-Dist: google-cloud-storage>=3.1.0
Requires-Dist: mock>=5.2.0
Requires-Dist: pandas>=2.2.3
Requires-Dist: pytest-cov>=6.0.0
Requires-Dist: python-dotenv>=1.0.1
Requires-Dist: requests-mock>=1.12.1
Requires-Dist: requests>=2.32.3
